[
  {
    "id": "quadratic-equations-001",
    "type": "MultiMC",
    "primarySkill": "quadratic-equations",
    "secondarySkills": [],
    "difficulty": 1,
    "stem": "Which values of \\(x\\) satisfy \\(x^2 - 5x + 6 = 0\\)? Select all that apply.",
    "options": [
      {
        "id": "A",
        "text": "2"
      },
      {
        "id": "B",
        "text": "3"
      },
      {
        "id": "C",
        "text": "-2"
      },
      {
        "id": "D",
        "text": "-3"
      }
    ],
    "answer": [
      "A",
      "B"
    ],
    "solutionStandard": "Factor: \\((x-2)(x-3)=0\\), so \\(x=2\\) or \\(x=3\\).",
    "timeTargetSec": 45
  },
  {
    "id": "quadratic-equations-002",
    "type": "Numeric",
    "primarySkill": "quadratic-equations",
    "secondarySkills": [],
    "difficulty": 1,
    "stem": "If \\(x^2 = 49\\) and \\(x < 0\\), what is the value of \\(x\\)?",
    "answer": -7,
    "solutionStandard": "\\(x = 7\\) or \\(x=-7\\). Since \\(x<0\\), \\(x=-7\\).",
    "timeTargetSec": 40
  },
  {
    "id": "quadratic-equations-003",
    "type": "MC",
    "primarySkill": "quadratic-equations",
    "secondarySkills": [],
    "difficulty": 2,
    "stem": "Solve: \\(x^2 - 5x = 0\\)",
    "options": [
      {
        "id": "A",
        "text": "\\(x = 5\\) only"
      },
      {
        "id": "B",
        "text": "\\(x = 0\\) only"
      },
      {
        "id": "C",
        "text": "\\(x = 0\\) or \\(x = 5\\)"
      },
      {
        "id": "D",
        "text": "\\(x = 0\\) or \\(x = -5\\)"
      },
      {
        "id": "E",
        "text": "No solution"
      }
    ],
    "answer": "C",
    "solutionStandard": "Factor: \\(x(x-5)=0\\), so \\(x=0\\) or \\(x=5\\). (Dividing both sides by \\(x\\) instead would incorrectly lose the solution \\(x=0\\).)",
    "timeTargetSec": 55
  },
  {
    "id": "quadratic-equations-004",
    "type": "QC",
    "primarySkill": "quadratic-equations",
    "secondarySkills": [],
    "difficulty": 2,
    "stem": "\\(x^2 - 4x - 21 = 0\\), and \\(x > 0\\)",
    "quantityA": "\\(x\\)",
    "quantityB": "\\(6\\)",
    "answer": "A",
    "solutionStandard": "Factor: \\((x-7)(x+3)=0\\), so \\(x=7\\) or \\(x=-3\\). Since \\(x>0\\), \\(x=7 > 6\\). Quantity A is greater.",
    "timeTargetSec": 65
  },
  {
    "id": "quadratic-equations-005",
    "type": "MC",
    "primarySkill": "quadratic-equations",
    "secondarySkills": [],
    "difficulty": 3,
    "stem": "The two roots of a quadratic equation are 4 and -6. Which of the following could be the equation?",
    "options": [
      {
        "id": "A",
        "text": "\\(x^2 + 2x - 24 = 0\\)"
      },
      {
        "id": "B",
        "text": "\\(x^2 - 2x - 24 = 0\\)"
      },
      {
        "id": "C",
        "text": "\\(x^2 + 10x + 24 = 0\\)"
      },
      {
        "id": "D",
        "text": "\\(x^2 - 10x - 24 = 0\\)"
      },
      {
        "id": "E",
        "text": "\\(x^2 + 2x + 24 = 0\\)"
      }
    ],
    "answer": "A",
    "solutionStandard": "The equation is \\((x-4)(x+6)=0\\), which expands to \\(x^2+2x-24=0\\).",
    "timeTargetSec": 70
  },
  {
    "id": "quadratic-equations-006",
    "type": "Numeric",
    "primarySkill": "quadratic-equations",
    "secondarySkills": [],
    "difficulty": 3,
    "stem": "If the sum of the two roots of \\(x^2 - kx + 20 = 0\\) is 9, and both roots are positive integers, what is the value of \\(k\\)?",
    "answer": 9,
    "solutionStandard": "The sum of the roots of \\(x^2-kx+20=0\\) is \\(k\\) (since sum \\(=-(-k)/1=k\\)). Given the sum is 9, \\(k=9\\). (Check: roots 4 and 5 multiply to 20 and sum to 9.)",
    "timeTargetSec": 75
  },
  {
    "id": "quadratic-equations-007",
    "type": "MC",
    "primarySkill": "quadratic-equations",
    "secondarySkills": [],
    "difficulty": 3,
    "stem": "Using the quadratic formula, what are the solutions to \\(x^2 + 2x - 5 = 0\\)?",
    "options": [
      {
        "id": "A",
        "text": "\\(-1 \\pm \\sqrt{6}\\)"
      },
      {
        "id": "B",
        "text": "\\(1 \\pm \\sqrt{6}\\)"
      },
      {
        "id": "C",
        "text": "\\(-2 \\pm \\sqrt{6}\\)"
      },
      {
        "id": "D",
        "text": "\\(-1 \\pm \\sqrt{5}\\)"
      },
      {
        "id": "E",
        "text": "\\(-1 \\pm 2\\sqrt{6}\\)"
      }
    ],
    "answer": "A",
    "solutionStandard": "\\(x = \\dfrac{-2 \\pm \\sqrt{4+20}}{2} = \\dfrac{-2 \\pm \\sqrt{24}}{2} = \\dfrac{-2 \\pm 2\\sqrt{6}}{2} = -1 \\pm \\sqrt{6}\\).",
    "timeTargetSec": 90
  },
  {
    "id": "quadratic-equations-008",
    "type": "MC",
    "primarySkill": "quadratic-equations",
    "secondarySkills": [],
    "difficulty": 4,
    "stem": "A rectangle's length is 3 more than its width, and its area is 40. What is the width?",
    "options": [
      {
        "id": "A",
        "text": "4"
      },
      {
        "id": "B",
        "text": "5"
      },
      {
        "id": "C",
        "text": "6"
      },
      {
        "id": "D",
        "text": "7"
      },
      {
        "id": "E",
        "text": "8"
      }
    ],
    "answer": "B",
    "solutionStandard": "Let width \\(=w\\). \\(w(w+3)=40\\), so \\(w^2+3w-40=0\\), factoring as \\((w-5)(w+8)=0\\). Since width is positive, \\(w=5\\).",
    "timeTargetSec": 85
  },
  {
    "id": "quadratic-equations-009",
    "type": "Numeric",
    "primarySkill": "quadratic-equations",
    "secondarySkills": [],
    "difficulty": 4,
    "stem": "If \\(x^2 - 8x + 16 = 0\\), what is the only value of \\(x\\)?",
    "answer": 4,
    "solutionStandard": "\\(x^2-8x+16=(x-4)^2=0\\), so \\(x=4\\) (a repeated root).",
    "timeTargetSec": 60
  },
  {
    "id": "quadratic-equations-010",
    "type": "QC",
    "primarySkill": "quadratic-equations",
    "secondarySkills": [],
    "difficulty": 4,
    "stem": "\\(x^2 + 6x + c = 0\\) has two distinct real roots.",
    "quantityA": "\\(c\\)",
    "quantityB": "\\(9\\)",
    "answer": "B",
    "solutionStandard": "For two distinct real roots, the discriminant must be positive: \\(36-4c>0\\), so \\(c<9\\). Quantity B is always greater.",
    "timeTargetSec": 85
  },
  {
    "id": "quadratic-equations-011",
    "type": "Numeric",
    "primarySkill": "quadratic-equations",
    "secondarySkills": [],
    "difficulty": 1,
    "variables": [
      {
        "name": "n",
        "min": 2,
        "max": 20,
        "step": 1
      }
    ],
    "stem": "If \\(x^2 = {{n*n}}\\) and \\(x > 0\\), what is the value of \\(x\\)?",
    "answer": 11,
    "answerFormula": "n",
    "solutionStandard": "\\(x = {{n}}\\) or \\(x = -{{n}}\\). Since \\(x>0\\), \\(x={{n}}\\).",
    "timeTargetSec": 40
  },
  {
    "id": "quadratic-equations-012",
    "type": "MC",
    "primarySkill": "quadratic-equations",
    "secondarySkills": [],
    "difficulty": 1,
    "stem": "Solve: \\(x^2 - 7x + 10 = 0\\)",
    "options": [
      {
        "id": "A",
        "text": "\\(x=2\\) or \\(x=5\\)"
      },
      {
        "id": "B",
        "text": "\\(x=-2\\) or \\(x=-5\\)"
      },
      {
        "id": "C",
        "text": "\\(x=1\\) or \\(x=10\\)"
      },
      {
        "id": "D",
        "text": "\\(x=2\\) only"
      },
      {
        "id": "E",
        "text": "No solution"
      }
    ],
    "answer": "A",
    "solutionStandard": "Factor: \\((x-2)(x-5)=0\\), so \\(x=2\\) or \\(x=5\\).",
    "timeTargetSec": 45
  },
  {
    "id": "quadratic-equations-013",
    "type": "Numeric",
    "primarySkill": "quadratic-equations",
    "secondarySkills": [],
    "difficulty": 2,
    "variables": [
      {
        "name": "p",
        "min": 1,
        "max": 15,
        "step": 1
      },
      {
        "name": "q",
        "min": 1,
        "max": 15,
        "step": 1
      }
    ],
    "stem": "The two roots of \\(x^2 - kx + {{p*q}} = 0\\) are both positive integers and sum to {{p+q}}. What is the value of \\(k\\)?",
    "answer": 13,
    "answerFormula": "p + q",
    "solutionStandard": "The sum of the roots of \\(x^2-kx+{{p*q}}=0\\) equals \\(k\\). Since the sum is given as \\({{p+q}}\\), \\(k={{p+q}}\\).",
    "timeTargetSec": 65
  },
  {
    "id": "quadratic-equations-014",
    "type": "MC",
    "primarySkill": "quadratic-equations",
    "secondarySkills": [],
    "difficulty": 2,
    "stem": "The two roots of a quadratic equation are \\(-3\\) and \\(5\\). Which of the following could be the equation?",
    "options": [
      {
        "id": "A",
        "text": "\\(x^2 - 2x - 15 = 0\\)"
      },
      {
        "id": "B",
        "text": "\\(x^2 + 2x - 15 = 0\\)"
      },
      {
        "id": "C",
        "text": "\\(x^2 - 8x + 15 = 0\\)"
      },
      {
        "id": "D",
        "text": "\\(x^2 + 8x - 15 = 0\\)"
      },
      {
        "id": "E",
        "text": "\\(x^2 - 2x + 15 = 0\\)"
      }
    ],
    "answer": "A",
    "solutionStandard": "The equation is \\((x+3)(x-5)=0\\), which expands to \\(x^2-2x-15=0\\).",
    "timeTargetSec": 65
  },
  {
    "id": "quadratic-equations-015",
    "type": "QC",
    "primarySkill": "quadratic-equations",
    "secondarySkills": [],
    "difficulty": 3,
    "variables": [
      {
        "name": "r1",
        "min": 5,
        "max": 15,
        "step": 1
      },
      {
        "name": "r2",
        "min": -15,
        "max": -1,
        "step": 1
      }
    ],
    "stem": "\\(x^2 - ({{r1+r2}})x + {{r1*r2}} = 0\\), and \\(x > 0\\)",
    "quantityA": "\\(x\\)",
    "quantityB": "{{r1-1}}",
    "answer": "A",
    "solutionStandard": "The equation factors as \\((x-{{r1}})(x-{{r2}}) = 0\\), giving roots \\({{r1}}\\) and \\({{r2}}\\). Since \\(x>0\\), \\(x={{r1}}\\), which is always 1 more than Quantity B. Quantity A is greater.",
    "timeTargetSec": 80
  },
  {
    "id": "quadratic-equations-016",
    "type": "MultiMC",
    "primarySkill": "quadratic-equations",
    "secondarySkills": [],
    "difficulty": 3,
    "stem": "Which values of \\(x\\) satisfy \\(x^2 - x - 12 = 0\\)? Select all that apply.",
    "options": [
      {
        "id": "A",
        "text": "4"
      },
      {
        "id": "B",
        "text": "-3"
      },
      {
        "id": "C",
        "text": "3"
      },
      {
        "id": "D",
        "text": "-4"
      }
    ],
    "answer": [
      "A",
      "B"
    ],
    "solutionStandard": "Factor: \\((x-4)(x+3)=0\\), so \\(x=4\\) or \\(x=-3\\).",
    "timeTargetSec": 50
  },
  {
    "id": "quadratic-equations-017",
    "type": "Numeric",
    "primarySkill": "quadratic-equations",
    "secondarySkills": [],
    "difficulty": 3,
    "variables": [
      {
        "name": "p",
        "min": 2,
        "max": 10,
        "step": 1
      }
    ],
    "stem": "The two roots of \\(x^2 - 12x + k = 0\\) are both positive integers, and one root is {{p}}. What is the other root?",
    "answer": 10,
    "answerFormula": "12 - p",
    "solutionStandard": "The sum of the roots is always 12 (the coefficient of \\(x\\), negated). If one root is \\({{p}}\\), the other is \\(12-{{p}}={{12-p}}\\).",
    "timeTargetSec": 70
  },
  {
    "id": "quadratic-equations-018",
    "type": "MC",
    "primarySkill": "quadratic-equations",
    "secondarySkills": [],
    "difficulty": 4,
    "stem": "Using the quadratic formula, what are the solutions to \\(x^2 - 4x - 1 = 0\\)?",
    "options": [
      {
        "id": "A",
        "text": "\\(2 \\pm \\sqrt{5}\\)"
      },
      {
        "id": "B",
        "text": "\\(-2 \\pm \\sqrt{5}\\)"
      },
      {
        "id": "C",
        "text": "\\(4 \\pm \\sqrt{5}\\)"
      },
      {
        "id": "D",
        "text": "\\(2 \\pm \\sqrt{20}\\)"
      },
      {
        "id": "E",
        "text": "\\(1 \\pm \\sqrt{5}\\)"
      }
    ],
    "answer": "A",
    "solutionStandard": "\\(x = \\dfrac{4 \\pm \\sqrt{16+4}}{2} = \\dfrac{4 \\pm \\sqrt{20}}{2} = \\dfrac{4 \\pm 2\\sqrt5}{2} = 2 \\pm \\sqrt5\\).",
    "timeTargetSec": 95
  },
  {
    "id": "quadratic-equations-019",
    "type": "Numeric",
    "primarySkill": "quadratic-equations",
    "secondarySkills": [],
    "difficulty": 5,
    "variables": [
      {
        "name": "wt",
        "min": 3,
        "max": 15,
        "step": 1
      },
      {
        "name": "d",
        "min": 1,
        "max": 10,
        "step": 1
      }
    ],
    "stem": "A rectangle's length is {{d}} more than its width, and its area is {{wt*(wt+d)}}. What is the width?",
    "answer": 6,
    "answerFormula": "wt",
    "solutionStandard": "Let width \\(=w\\). \\(w(w+{{d}}) = {{wt*(wt+d)}}\\) has exactly one positive solution, \\(w={{wt}}\\) (check: \\({{wt}}\\times({{wt}}+{{d}}) = {{wt*(wt+d)}}\\)).",
    "timeTargetSec": 85
  },
  {
    "id": "quadratic-equations-020",
    "type": "QC",
    "primarySkill": "quadratic-equations",
    "secondarySkills": [],
    "difficulty": 5,
    "stem": "\\(x^2 + bx + 16 = 0\\) has no real roots.",
    "quantityA": "\\(b^2\\)",
    "quantityB": "\\(64\\)",
    "answer": "B",
    "solutionStandard": "No real roots means the discriminant is negative: \\(b^2 - 64 < 0\\), so \\(b^2 < 64\\). Quantity B is always greater.",
    "timeTargetSec": 85
  }
]
